easyTkinter/__init__.py
easyTkinter/easy_auto_window.py
easyTkinter/easy_auto_window_size.py
easyTkinter/easy_button.py
easyTkinter/easy_check_button.py
easyTkinter/easy_drop_list.py
easyTkinter/easy_fade_animation.py
easyTkinter/easy_frame.py
easyTkinter/easy_label.py
easyTkinter/easy_mobile_animation.py
easyTkinter/easy_multi_text.py
easyTkinter/easy_popup_animation.py
easyTkinter/easy_progressbar.py
easyTkinter/easy_radio_button.py
easyTkinter/easy_scale.py
easyTkinter/easy_spinbox.py
easyTkinter/easy_text.py
easyTkinter/easy_warning_windows.py
easyTkinter/main.py
easyTkinter/test.py
etkinter-1.7.9.dist-info/LICENSE
etkinter-1.7.9.dist-info/METADATA
etkinter-1.7.9.dist-info/WHEEL
etkinter-1.7.9.dist-info/top_level.txt
etkinter-1.7.9.dist-info/RECORD
